README.md
setup.py
src/dipbot/__init__.py
src/dipbot/app.py
src/dipbot/bot.py
src/dipbot/bot_utilities.py
src/dipbot/cli.py
src/dipbot/data_definitions.py
src/dipbot/scraper.py
src/dipbot/utilities.py
src/dipbot.egg-info/PKG-INFO
src/dipbot.egg-info/SOURCES.txt
src/dipbot.egg-info/dependency_links.txt
src/dipbot.egg-info/entry_points.txt
src/dipbot.egg-info/not-zip-safe
src/dipbot.egg-info/requires.txt
src/dipbot.egg-info/top_level.txt
src/dipbot/cogs/__init__.py
src/dipbot/cogs/status.py