Metadata-Version: 2.1
Name: dipbot
Version: 0.12
Summary: webdiplomacy status reporter bot for discord
Home-page: https://github.com/circius/webdiplomacy-bot
Author: circius
Author-email: circius@posteo.de
License: UNKNOWN
Download-URL: https://github.com/circius/webdiplomacy-bot/archive/0.12.tar.gz
Keywords: webdiplomacy,bot,discord
Platform: UNKNOWN
Classifier: Development Status :: 3 - Alpha
Classifier: Programming Language :: Python :: 3
Classifier: License :: OSI Approved :: MIT License
Classifier: Topic :: Utilities
Requires-Python: >=3.6
